pexels_mcp_server/__init__.py
pexels_mcp_server/core.py
pexels_mcp_server/enums.py
pexels_mcp_server/schemas.py
pexels_mcp_server/server.py
pexels_mcp_server-0.0.4.dist-info/METADATA
pexels_mcp_server-0.0.4.dist-info/WHEEL
pexels_mcp_server-0.0.4.dist-info/entry_points.txt
pexels_mcp_server-0.0.4.dist-info/top_level.txt
pexels_mcp_server-0.0.4.dist-info/RECORD
