Metadata-Version: 2.4
Name: pexels-mcp-server
Version: 0.0.4
Summary: An MCP server for Pexels
Author-email: Gary Meng <guozao.m@gmail.com>
Project-URL: Homepage, https://github.com/garylab/pexels-mcp-server
Project-URL: Bug Tracker, https://github.com/garylab/pexels-mcp-server/issues
Project-URL: Author Blog, https://garymeng.com
Keywords: pexels,mcp,server,photos,videos
Requires-Python: >=3.11
Requires-Dist: aiohttp>=3.11.16
Requires-Dist: certifi>=2025.1.31
Requires-Dist: mcp[cli]>=1.6.0
Requires-Dist: pydantic>=2.11.2
Requires-Dist: python-dotenv>=1.1.0
